osvc_kalkulacka/__init__.py
osvc_kalkulacka/cli.py
osvc_kalkulacka/core.py
osvc_kalkulacka/epo.py
osvc_kalkulacka/data/__init__.py
osvc_kalkulacka/data/year_defaults.toml
osvc_kalkulacka/data/year_presets.example.toml
osvc_kalkulacka-0.8.5.dist-info/METADATA
osvc_kalkulacka-0.8.5.dist-info/WHEEL
osvc_kalkulacka-0.8.5.dist-info/entry_points.txt
osvc_kalkulacka-0.8.5.dist-info/RECORD
