Metadata-Version: 2.4
Name: osvc-kalkulacka
Version: 0.8.5
Summary: OSVČ kalkulačka (DPFO + ZP/SP)
Project-URL: Homepage, https://github.com/fertek/osvc-kalkulacka
Project-URL: Issues, https://github.com/fertek/osvc-kalkulacka/issues
Project-URL: Changelog, https://github.com/fertek/osvc-kalkulacka/blob/main/CHANGELOG.md
Author-email: Jan Feřtek <jf@fertek.cz>
License: MIT
Classifier: Environment :: Console
Classifier: Intended Audience :: End Users/Desktop
Classifier: License :: OSI Approved :: MIT License
Classifier: Programming Language :: Python :: 3
Classifier: Programming Language :: Python :: 3.11
Classifier: Programming Language :: Python :: 3.12
Classifier: Programming Language :: Python :: 3.13
Classifier: Topic :: Office/Business :: Financial :: Accounting
Classifier: Topic :: Utilities
Requires-Python: >=3.11
Requires-Dist: click>=8.1
